LICENSE
MANIFEST.in
README.rst
requirements.txt
setup.py
topgg/__init__.py
topgg/autopost.py
topgg/client.py
topgg/data.py
topgg/errors.py
topgg/http.py
topgg/ratelimiter.py
topgg/types.py
topgg/webhook.py
topggpy_disnake.egg-info/PKG-INFO
topggpy_disnake.egg-info/SOURCES.txt
topggpy_disnake.egg-info/dependency_links.txt
topggpy_disnake.egg-info/requires.txt
topggpy_disnake.egg-info/top_level.txt