Metadata-Version: 2.1
Name: topggpy-disnake
Version: 2.0.1
Summary: A simple API wrapper for Top.gg written in Python.
Home-page: https://github.com/zachnieto/topggpy-disnake
Author: Zach Nieto
Author-email: zachnieto14@gmail.com
Maintainer: Zach Nieto
License: MIT
Keywords: discord bot server list discordservers serverlist discordbots botlist topgg top.gg
Platform: UNKNOWN
Classifier: Development Status :: 5 - Production/Stable
Classifier: License :: OSI Approved :: MIT License
Classifier: Intended Audience :: Developers
Classifier: Natural Language :: English
Classifier: Operating System :: OS Independent
Classifier: Programming Language :: Python :: 3 :: Only
Classifier: Programming Language :: Python :: 3.6
Classifier: Programming Language :: Python :: 3.7
Classifier: Programming Language :: Python :: 3.8
Classifier: Programming Language :: Python :: 3.9
Classifier: Topic :: Internet
Classifier: Topic :: Software Development :: Libraries
Classifier: Topic :: Software Development :: Libraries :: Python Modules
Classifier: Topic :: Utilities
Requires-Python: >= 3.6
License-File: LICENSE
